package pkg;

super public class TestLegacyTernaryReferenceCast
  version 47:0
{

public Method "<init>":"()V"
  stack 1 locals 1
{
  aload_0;
  invokespecial Method java/lang/Object."<init>":"()V";
  return;
}

public Method "choose":"(Z)Lpkg/TestLegacyTernaryReferenceCastBase;"
  stack 2 locals 2
{
  iload_1;
  ifeq LRight;
  new class pkg/TestLegacyTernaryReferenceCastLeft;
  dup;
  invokespecial Method pkg/TestLegacyTernaryReferenceCastLeft."<init>":"()V";
  goto LReturn;
LRight:
  new class pkg/TestLegacyTernaryReferenceCastRight;
  dup;
  invokespecial Method pkg/TestLegacyTernaryReferenceCastRight."<init>":"()V";
LReturn:
  areturn;
}

public Method "chooseObject":"(Z)Ljava/lang/Object;"
  stack 2 locals 2
{
  iload_1;
  ifeq LBytes;
  new class pkg/TestLegacyTernaryReferenceCastLeft;
  dup;
  invokespecial Method pkg/TestLegacyTernaryReferenceCastLeft."<init>":"()V";
  goto LReturnObject;
LBytes:
  iconst_1;
  newarray byte;
LReturnObject:
  areturn;
}

public Method "chooseObjectReversed":"(Z)Ljava/lang/Object;"
  stack 2 locals 2
{
  iload_1;
  ifeq LClass;
  iconst_1;
  newarray byte;
  goto LReturnObjectReversed;
LClass:
  new class pkg/TestLegacyTernaryReferenceCastLeft;
  dup;
  invokespecial Method pkg/TestLegacyTernaryReferenceCastLeft."<init>":"()V";
LReturnObjectReversed:
  areturn;
}

public Method "chooseReferenceArray":"(Z)[Ljava/lang/Object;"
  stack 2 locals 2
{
  iload_1;
  ifeq LIntegerArray;
  iconst_1;
  anewarray class java/lang/String;
  goto LReturnReferenceArray;
LIntegerArray:
  iconst_1;
  anewarray class java/lang/Integer;
LReturnReferenceArray:
  areturn;
}

// JVM reference comparison is untyped, but Java source rejects equality between
// sibling classes after the CHECKCAST results have been stored in narrow locals.
public static Method "compareNarrowed":"(Lpkg/TestLegacyTernaryReferenceCastBase;Lpkg/TestLegacyTernaryReferenceCastBase;)Z"
  stack 2 locals 4
{
  aload_0;
  checkcast pkg/TestLegacyTernaryReferenceCastLeft;
  astore_2;
  aload_1;
  checkcast pkg/TestLegacyTernaryReferenceCastRight;
  astore_3;
  aload_2;
  invokevirtual Method pkg/TestLegacyTernaryReferenceCastLeft.touch:"()V";
  aload_3;
  invokevirtual Method pkg/TestLegacyTernaryReferenceCastRight.touch:"()V";
  aload_2;
  aload_3;
  if_acmpne LDifferent;
  iconst_0;
  ireturn;
LDifferent:
  iconst_1;
  ireturn;
}

public static Method "compareRelated":"(Lpkg/TestLegacyTernaryReferenceCastBase;Lpkg/TestLegacyTernaryReferenceCastLeft;)Z"
  stack 2 locals 2
{
  aload_0;
  aload_1;
  if_acmpeq LSame;
  iconst_0;
  ireturn;
LSame:
  iconst_1;
  ireturn;
}

public static Method "compareSiblingArrays":"([Ljava/lang/String;[Ljava/lang/Integer;)Z"
  stack 2 locals 2
{
  aload_0;
  aload_1;
  if_acmpne LDifferentArrays;
  iconst_0;
  ireturn;
LDifferentArrays:
  iconst_1;
  ireturn;
}

public static Method "comparePrimitiveArrays":"([I[J)Z"
  stack 2 locals 2
{
  aload_0;
  aload_1;
  if_acmpne LDifferentPrimitiveArrays;
  iconst_0;
  ireturn;
LDifferentPrimitiveArrays:
  iconst_1;
  ireturn;
}

} // end Class TestLegacyTernaryReferenceCast
